image-enlarge/__init__.py
image-enlarge/__main__.py
img_en/__init__.py
img_en/__main__.py
img_en-0.1.dist-info/LICENSE.txt
img_en-0.1.dist-info/METADATA
img_en-0.1.dist-info/WHEEL
img_en-0.1.dist-info/top_level.txt
img_en-0.1.dist-info/RECORD
