Metadata-Version: 2.1
Name: img-en
Version: 0.1
Summary: It takes img and int zoom level and output zoomed image.
Home-page: https://www.youtube.com/channel/UC_7_s7TPjHp2WgCJAbyKLOg
Author: Sarthak Karki
Author-email: srthk7338@gmail.com
License: MIT
Keywords: zoom
Platform: UNKNOWN
Classifier: License :: OSI Approved :: MIT License
Classifier: Programming Language :: Python :: 3
Classifier: Programming Language :: Python :: 3.7
Classifier: Programming Language :: Python :: 3.8
Classifier: Programming Language :: Python :: 3.9
Requires-Dist: opencv-python (==4.4.0.44)
Requires-Dist: numpy (==1.19.3)
